LICENSE
MANIFEST.in
README.rst
setup.py
switches.py
switches.egg-info/PKG-INFO
switches.egg-info/SOURCES.txt
switches.egg-info/dependency_links.txt
switches.egg-info/top_level.txt