Metadata-Version: 1.0
Name: switches
Version: 0.1.1
Summary: Friendly Command Line Scripts
Home-page: https://github.com/dirn/switches
Author: Andy Dirnberger
Author-email: dirn@dirnonline.com
License: Copyright (c) 2012, Andy Dirnberger
